alphafund/__init__.py
alphafund-0.0.1.dev1.dist-info/LICENSE
alphafund-0.0.1.dev1.dist-info/METADATA
alphafund-0.0.1.dev1.dist-info/WHEEL
alphafund-0.0.1.dev1.dist-info/RECORD
